[
    "index.html",
    {
        "filename": "intro-dev-tooling.html",
        "attr": {
            "data-background": "#000000"
        }
    },
    {
        "filename": "automate.html",
        "attr": {
            "data-background": "#000000"
        }
    },    
    {
        "filename": "node.html",
        "attr": {
            "data-background": "#000000"
        }
    },
    {
        "filename": "toolkit.html",
        "attr": {
            "data-background": "#000000"
        }
    },
    [
        {
            "filename": "scaffolding.html",
            "attr": {
                "data-background": "#000000"
            }
        },
        {
            "filename": "yeoman.html",
            "attr": {
                "data-background": "#000000"
            }
        }
    ],
    [
        {
            "filename": "package-management.html",
            "attr": {
                "data-background": "#000000"
            }
        },
        {
            "filename": "bower.html",
            "attr": {
                "data-background": "#000000"
            }
        },
        {
            "filename": "bower-json.html",
            "attr": {
                "data-background": "#000000"
            }
        },
        {
            "filename": "npm.html",
            "attr": {
                "data-background": "#000000"
            }
        }
    ],
    [
        {
            "filename": "build-and-deploy.html",
            "attr": {
                "data-background": "#000000"
            }
        },
        {
            "filename": "gulp.html",
            "attr": {
                "data-background": "#000000"
            }
        },
        {
            "filename": "gulp-json.html",
            "attr": {
                "data-background": "#000000"
            }
        },
        {
            "filename": "grunt.html",
            "attr": {
                "data-background": "#000000"
            }
        }
    ],
    [
        {
            "filename": "version-control.html",
            "attr": {
                "data-background": "#000000"
            }
        },
        {
            "filename": "git.html",
            "attr": {
                "data-background": "#000000"
            }
        }
    ],
    {
        "filename": "gss.html",
        "attr": {
            "data-background": "#000000"
        }
    },
    {
        "filename": "caching.html",
        "attr": {
            "data-background": "#000000"
        }
    },    
    {
        "filename": "markdown.html",
        "attr": {
            "data-background": "#000000"
        }
    }

]